.VERSION
AUTHORS.rst
CONTRIBUTING.rst
HISTORY.rst
LICENSE
MANIFEST.in
Pipfile
Pipfile.lock
README.rst
USAGE.rst
dev-requirements.txt
requirements.txt
setup.cfg
setup.py
docs/Makefile
docs/authors.rst
docs/conf.py
docs/contributing.rst
docs/history.rst
docs/index.rst
docs/installation.rst
docs/readme.rst
docs/usage.rst
enpassreadercli/.VERSION
enpassreadercli/AUTHORS.rst
enpassreadercli/CONTRIBUTING.rst
enpassreadercli/HISTORY.rst
enpassreadercli/LICENSE
enpassreadercli/Pipfile
enpassreadercli/Pipfile.lock
enpassreadercli/README.rst
enpassreadercli/USAGE.rst
enpassreadercli/__init__.py
enpassreadercli/_version.py
enpassreadercli/dev-requirements.txt
enpassreadercli/enpassreadercli.py
enpassreadercli/enpassreadercliexceptions.py
enpassreadercli/requirements.txt
enpassreadercli.egg-info/PKG-INFO
enpassreadercli.egg-info/SOURCES.txt
enpassreadercli.egg-info/dependency_links.txt
enpassreadercli.egg-info/entry_points.txt
enpassreadercli.egg-info/not-zip-safe
enpassreadercli.egg-info/requires.txt
enpassreadercli.egg-info/top_level.txt
enpassreadercli/__pycache__/__init__.cpython-39.pyc
enpassreadercli/__pycache__/_version.cpython-39.pyc
enpassreadercli/conf/logging.json-example
tests/test_enpassreadercli.py