Metadata-Version: 2.4
Name: enpassreadercli
Version: 0.4.3
Summary: A cli to access enpass 6 encrypted databases and read, list and search values.
Home-page: https://github.com/costastf/enpassreadercli
Author: Costas Tyfoxylos
Author-email: costas.tyf@gmail.com
License: MIT
Keywords: enpassreadercli enpass
Classifier: Development Status :: 4 - Beta
Classifier: Intended Audience :: Developers
Classifier: License :: OSI Approved :: MIT License
Classifier: Natural Language :: English
Classifier: Programming Language :: Python :: 3.7
License-File: LICENSE
License-File: AUTHORS.rst
Requires-Dist: coloredlogs>=15.0.1; python_version >= "2.7" and python_version not in "3.0, 3.1, 3.2, 3.3, 3.4"
Requires-Dist: enpassreaderlib>=0.2.6
Requires-Dist: prompt-toolkit>=3.0.51; python_version >= "3.8"
Requires-Dist: pyotp>=2.9.0; python_version >= "3.7"
Dynamic: author
Dynamic: author-email
Dynamic: classifier
Dynamic: description
Dynamic: home-page
Dynamic: keywords
Dynamic: license
Dynamic: license-file
Dynamic: requires-dist
Dynamic: summary
